horizon/__init__.py
horizon/module.py
horizon-beyond/__init__.py
horizon-beyond/module.py
horizon_beyond-0.1.1.dist-info/LICENSE
horizon_beyond-0.1.1.dist-info/METADATA
horizon_beyond-0.1.1.dist-info/WHEEL
horizon_beyond-0.1.1.dist-info/entry_points.txt
horizon_beyond-0.1.1.dist-info/top_level.txt
horizon_beyond-0.1.1.dist-info/RECORD
